{"trial_id": "134", "hyperparameters": {"space": [{"class_name": "Int", "config": {"name": "filters", "default": null, "conditions": [], "min_value": 10, "max_value": 150, "step": 5, "sampling": "linear"}}, {"class_name": "Choice", "config": {"name": "pool_size", "default": 2, "conditions": [], "values": [2, 3], "ordered": true}}, {"class_name": "Choice", "config": {"name": "learning_rate", "default": 0.01, "conditions": [], "values": [0.01, 0.001, 0.0001], "ordered": true}}], "values": {"filters": 130, "pool_size": 2, "learning_rate": 0.01}}, "metrics": {"metrics": {"loss": {"direction": "min", "observations": [{"value": [2467204.75], "step": 9}]}, "mae": {"direction": "min", "observations": [{"value": [1155.0118408203125], "step": 9}]}, "mean_absolute_percentage_error": {"direction": "min", "observations": [{"value": [3.265749931335449], "step": 9}]}, "val_loss": {"direction": "min", "observations": [{"value": [336900.0], "step": 9}]}, "val_mae": {"direction": "min", "observations": [{"value": [449.84942626953125], "step": 9}]}, "val_mean_absolute_percentage_error": {"direction": "min", "observations": [{"value": [2.2671923637390137], "step": 9}]}}}, "score": 2.2671923637390137, "best_step": 9, "status": "COMPLETED", "message": null}