{"trial_id": "090", "hyperparameters": {"space": [{"class_name": "Int", "config": {"name": "filters", "default": null, "conditions": [], "min_value": 10, "max_value": 150, "step": 5, "sampling": "linear"}}, {"class_name": "Choice", "config": {"name": "pool_size", "default": 2, "conditions": [], "values": [2, 3], "ordered": true}}, {"class_name": "Choice", "config": {"name": "learning_rate", "default": 0.01, "conditions": [], "values": [0.01, 0.001, 0.0001], "ordered": true}}], "values": {"filters": 145, "pool_size": 3, "learning_rate": 0.01}}, "metrics": {"metrics": {"loss": {"direction": "min", "observations": [{"value": [300530.78125], "step": 41}]}, "mae": {"direction": "min", "observations": [{"value": [386.1116027832031], "step": 41}]}, "mean_absolute_percentage_error": {"direction": "min", "observations": [{"value": [4.2398905754089355], "step": 41}]}, "val_loss": {"direction": "min", "observations": [{"value": [7925.74853515625], "step": 41}]}, "val_mae": {"direction": "min", "observations": [{"value": [45.57998275756836], "step": 41}]}, "val_mean_absolute_percentage_error": {"direction": "min", "observations": [{"value": [0.7090184688568115], "step": 41}]}}}, "score": 0.7090184688568115, "best_step": 41, "status": "COMPLETED", "message": null}