{"trial_id": "125", "hyperparameters": {"space": [{"class_name": "Int", "config": {"name": "filters", "default": null, "conditions": [], "min_value": 10, "max_value": 150, "step": 5, "sampling": "linear"}}, {"class_name": "Choice", "config": {"name": "pool_size", "default": 2, "conditions": [], "values": [2, 3], "ordered": true}}, {"class_name": "Choice", "config": {"name": "learning_rate", "default": 0.01, "conditions": [], "values": [0.01, 0.001, 0.0001], "ordered": true}}], "values": {"filters": 105, "pool_size": 2, "learning_rate": 0.0001}}, "metrics": {"metrics": {"loss": {"direction": "min", "observations": [{"value": [614.754150390625], "step": 68}]}, "mae": {"direction": "min", "observations": [{"value": [12.804682731628418], "step": 68}]}, "mean_absolute_percentage_error": {"direction": "min", "observations": [{"value": [2.1781415939331055], "step": 68}]}, "val_loss": {"direction": "min", "observations": [{"value": [21452.904296875], "step": 68}]}, "val_mae": {"direction": "min", "observations": [{"value": [110.70265197753906], "step": 68}]}, "val_mean_absolute_percentage_error": {"direction": "min", "observations": [{"value": [3.752689838409424], "step": 68}]}}}, "score": 3.752689838409424, "best_step": 68, "status": "COMPLETED", "message": null}