{"trial_id": "037", "hyperparameters": {"space": [{"class_name": "Int", "config": {"name": "units", "default": null, "conditions": [], "min_value": 10, "max_value": 200, "step": 10, "sampling": "linear"}}, {"class_name": "Choice", "config": {"name": "learning_rate", "default": 0.01, "conditions": [], "values": [0.01, 0.001, 0.0001], "ordered": true}}], "values": {"units": 100, "learning_rate": 0.001}}, "metrics": {"metrics": {"loss": {"direction": "min", "observations": [{"value": [0.0023532251361757517], "step": 5}]}, "mae": {"direction": "min", "observations": [{"value": [0.03396094962954521], "step": 5}]}, "mean_absolute_percentage_error": {"direction": "min", "observations": [{"value": [9.770442008972168], "step": 5}]}, "val_loss": {"direction": "min", "observations": [{"value": [0.00018343077681493014], "step": 5}]}, "val_mae": {"direction": "min", "observations": [{"value": [0.010605300776660442], "step": 5}]}, "val_mean_absolute_percentage_error": {"direction": "min", "observations": [{"value": [5.233234405517578], "step": 5}]}}}, "score": 5.233234405517578, "best_step": 5, "status": "COMPLETED", "message": null}