{"trial_id": "093", "hyperparameters": {"space": [{"class_name": "Int", "config": {"name": "filters", "default": null, "conditions": [], "min_value": 10, "max_value": 150, "step": 5, "sampling": "linear"}}, {"class_name": "Choice", "config": {"name": "pool_size", "default": 2, "conditions": [], "values": [2, 3], "ordered": true}}, {"class_name": "Choice", "config": {"name": "learning_rate", "default": 0.01, "conditions": [], "values": [0.01, 0.001, 0.0001], "ordered": true}}], "values": {"filters": 115, "pool_size": 2, "learning_rate": 0.01}}, "metrics": {"metrics": {"accuracy": {"direction": "max", "observations": [{"value": [0.47278910875320435], "step": 2}]}, "loss": {"direction": "min", "observations": [{"value": [0.6932125687599182], "step": 2}]}, "val_accuracy": {"direction": "max", "observations": [{"value": [0.6774193644523621], "step": 2}]}, "val_loss": {"direction": "min", "observations": [{"value": [0.6929009556770325], "step": 2}]}}}, "score": 0.6774193644523621, "best_step": 2, "status": "COMPLETED", "message": null}