{"ongoing_trials": {}, "hyperparameters": {"space": [{"class_name": "Int", "config": {"name": "conv_1_filter", "default": null, "conditions": [], "min_value": 10, "max_value": 150, "step": 10, "sampling": "linear"}}, {"class_name": "Choice", "config": {"name": "pool_1_size", "default": 2, "conditions": [], "values": [2, 3], "ordered": true}}, {"class_name": "Int", "config": {"name": "conv_2_filter", "default": null, "conditions": [], "min_value": 10, "max_value": 150, "step": 10, "sampling": "linear"}}, {"class_name": "Choice", "config": {"name": "pool_2_size", "default": 2, "conditions": [], "values": [2, 3], "ordered": true}}, {"class_name": "Int", "config": {"name": "dense_units", "default": null, "conditions": [], "min_value": 10, "max_value": 100, "step": 10, "sampling": "linear"}}, {"class_name": "Int", "config": {"name": "lstm_units", "default": null, "conditions": [], "min_value": 10, "max_value": 100, "step": 10, "sampling": "linear"}}, {"class_name": "Float", "config": {"name": "dropout_2", "default": 0.1, "conditions": [], "min_value": 0.1, "max_value": 0.5, "step": 0.1, "sampling": "linear"}}, {"class_name": "Choice", "config": {"name": "learning_rate", "default": 0.01, "conditions": [], "values": [0.01, 0.001, 0.0001], "ordered": true}}], "values": {"conv_1_filter": 10, "pool_1_size": 2, "conv_2_filter": 10, "pool_2_size": 2, "dense_units": 10, "lstm_units": 10, "dropout_2": 0.1, "learning_rate": 0.01}}, "start_order": ["000", "001", "002", "003", "004", "005", "006", "007", "008", "009", "010", "011", "012", "013", "014", "015", "016", "017", "018", "019", "020", "021", "022", "023", "024", "025", "026", "027", "028", "029", "030", "031", "032", "033", "034", "035", "036", "037", "038", "039", "040", "041", "042", "043", "044", "045", "046", "047", "048", "049", "050", "051", "052", "053", "054", "055", "056", "057", "058", "059", "060", "061", "062", "063", "064", "065", "066", "067", "068", "069", "070", "071", "072", "073", "074", "075", "076", "077", "078", "079", "080", "081", "082", "083", "084", "085", "086", "087", "088", "089", "090", "091", "092", "093", "094", "095", "096", "097", "098", "099", "100", "101", "102", "103", "104", "105", "106", "107", "108", "109", "110", "111", "112", "113", "114", "115", "116", "117", "118", "119", "120", "121", "122", "123", "124", "125", "126", "127", "128", "129", "130", "131", "132", "133", "134", "135", "136", "137", "138", "139", "140", "141", "142", "143", "144", "145", "146", "147", "148", "149", "150", "151", "152", "153", "154", "155", "156", "157", "158", "159", "160", "161", "162", "163", "164", "165", "166", "167", "168", "169", "170", "171", "172", "173", "174", "175", "176", "177", "178", "179", "180", "181", "182", "183", "184", "185", "186", "187", "188", "189", "190", "191", "192", "193", "194", "195", "196", "197", "198", "199"], "end_order": ["000", "001", "002", "003", "004", "005", "006", "007", "008", "009", "010", "011", "012", "013", "014", "015", "016", "017", "018", "019", "020", "021", "022", "023", "024", "025", "026", "027", "028", "029", "030", "031", "032", "033", "034", "035", "036", "037", "038", "039", "040", "041", "042", "043", "044", "045", "046", "047", "048", "049", "050", "051", "052", "053", "054", "055", "056", "057", "058", "059", "060", "061", "062", "063", "064", "065", "066", "067", "068", "069", "070", "071", "072", "073", "074", "075", "076", "077", "078", "079", "080", "081", "082", "083", "084", "085", "086", "087", "088", "089", "090", "091", "092", "093", "094", "095", "096", "097", "098", "099", "100", "101", "102", "103", "104", "105", "106", "107", "108", "109", "110", "111", "112", "113", "114", "115", "116", "117", "118", "119", "120", "121", "122", "123", "124", "125", "126", "127", "128", "129", "130", "131", "132", "133", "134", "135", "136", "137", "138", "139", "140", "141", "142", "143", "144", "145", "146", "147", "148", "149", "150", "151", "152", "153", "154", "155", "156", "157", "158", "159", "160", "161", "162", "163", "164", "165", "166", "167", "168", "169", "170", "171", "172", "173", "174", "175", "176", "177", "178", "179", "180", "181", "182", "183", "184", "185", "186", "187", "188", "189", "190", "191", "192", "193", "194", "195", "196", "197", "198", "199"], "run_times": {"000": 1, "001": 1, "002": 1, "003": 1, "004": 1, "005": 1, "006": 1, "007": 1, "008": 1, "009": 1, "010": 1, "011": 1, "012": 1, "013": 1, "014": 1, "015": 1, "016": 1, "017": 1, "018": 1, "019": 1, "020": 1, "021": 1, "022": 1, "023": 1, "024": 1, "025": 1, "026": 1, "027": 1, "028": 1, "029": 1, "030": 1, "031": 1, "032": 1, "033": 1, "034": 1, "035": 1, "036": 1, "037": 1, "038": 1, "039": 1, "040": 1, "041": 1, "042": 1, "043": 1, "044": 1, "045": 1, "046": 1, "047": 1, "048": 1, "049": 1, "050": 1, "051": 1, "052": 1, "053": 1, "054": 1, "055": 1, "056": 1, "057": 1, "058": 1, "059": 1, "060": 1, "061": 1, "062": 1, "063": 1, "064": 1, "065": 1, "066": 1, "067": 1, "068": 1, "069": 1, "070": 1, "071": 1, "072": 1, "073": 1, "074": 1, "075": 1, "076": 1, "077": 1, "078": 1, "079": 1, "080": 1, "081": 1, "082": 1, "083": 1, "084": 1, "085": 1, "086": 1, "087": 1, "088": 1, "089": 1, "090": 1, "091": 1, "092": 1, "093": 1, "094": 1, "095": 1, "096": 1, "097": 1, "098": 1, "099": 1, "100": 1, "101": 1, "102": 1, "103": 1, "104": 1, "105": 1, "106": 1, "107": 1, "108": 1, "109": 1, "110": 1, "111": 1, "112": 1, "113": 1, "114": 1, "115": 1, "116": 1, "117": 1, "118": 1, "119": 1, "120": 1, "121": 1, "122": 1, "123": 1, "124": 1, "125": 1, "126": 1, "127": 1, "128": 1, "129": 1, "130": 1, "131": 1, "132": 1, "133": 1, "134": 1, "135": 1, "136": 1, "137": 1, "138": 1, "139": 1, "140": 1, "141": 1, "142": 1, "143": 1, "144": 1, "145": 1, "146": 1, "147": 1, "148": 1, "149": 1, "150": 1, "151": 1, "152": 1, "153": 1, "154": 1, "155": 1, "156": 1, "157": 1, "158": 1, "159": 1, "160": 1, "161": 1, "162": 1, "163": 1, "164": 1, "165": 1, "166": 1, "167": 1, "168": 1, "169": 1, "170": 1, "171": 1, "172": 1, "173": 1, "174": 1, "175": 1, "176": 1, "177": 1, "178": 1, "179": 1, "180": 1, "181": 1, "182": 1, "183": 1, "184": 1, "185": 1, "186": 1, "187": 1, "188": 1, "189": 1, "190": 1, "191": 1, "192": 1, "193": 1, "194": 1, "195": 1, "196": 1, "197": 1, "198": 1, "199": 1}, "retry_queue": [], "seed": 3805, "seed_state": 5405, "tried_so_far": ["b93b8e46fe56346ca613354a30b2a0f3", "fb9b91e540d93b6b2d2bf138e1d99e30", "6b13932ee7ea8f8a68cfd00e010beac8", "ee309d77abd0848eef989782b9b545a5", "6b21dcf618e4cdfaf7f10319abb3f709", "3d53be6da553f3ff10862297b6e918e6", "ae86fcb44a462abe39a4284cc576df7d", "6956535727e4d6cd4d5fb8fd9ee3bc23", "2b18f8178919d2ed2513efad489c46f4", "644f62971fc31354275f81d7254bfe57", "f2592e7f3e0eb2991c18012268e5b3b9", "ddce2097be3eebc6c4a64deac3a8e5ba", "e6b2bf50f832321d1a7ee989d257b42f", "7dd7af5c78f673a3d0e59314f11db5b6", "28bf55258a4338e0c4e24286e432162f", "d43e1d4b8cb42f7b7b2106eabf58157c", "eb410acb3dfa34b6b906f80aeb50ec33", "f6cb30c38a97d5b084128bad7b1839e0", "02f980092269d49c8a5c169f66e2a3f5", "41776741a182f625a2df8842a2ee59e7", "978e70615695cba74f6e77aff7bc5107", "4d41175d626ac093f9dd53e857f89714", "3d46e261b3358965c36da7f8e5dfbbd4", "b61b435b07572cd437577369271f3113", "4979638815b14ec2ae67d5aa8ddfbe24", "9ce49cda8497f2d37d7e7ec1c08f17aa", "4c458dffba36748af2acdcd89f701c92", "0308d02fc1dabf340e74cdcb4b216f9f", "3a119050249b0cb2761edf60d08bb8ed", "5014d28977f52eded1898f008862e578", "1e2c8c15591647bc5e85289f7e337c7d", "2e944273885bd9265d94b2a7e9b4d4eb", "06045fccc6384f5f13f7b7d275992c54", "1209f43304bbf42b0b116b7f6571a5e9", "4704e8b36fc8dcae70e49b9818ab4215", "1b54b2ede16e50fcd7d4747027dc2072", "5b9ae7c1cb17d4dc5e5db93da254b099", "40ed71c0a344839367ffddc61d277a4a", "53965d1a71cafa0a66c91486fd89daf9", "bbe22e00ea6e37e7aa61f607a9bd45d9", "b9628d8665064b807eb2ccfe774c8808", "b19e601ae8d231a6ed244d1dc4713eff", "f943b653ba7dd1a79c3427b1ee5bcb95", "e7e209e9a2b65a1e5c6222d1f2b833a7", "4ab5fc26ca1d6be4efb463516811122e", "c07089798ca0bae26808eb35eaaf82de", "8beb19396b632eae86f8e0aa051516c2", "f935909891e9df8f5c6d5d6eb1847929", "493ce4cebc7ae4d31603b1926a46f18d", "d8ba8477cff1af51891c3d1586e40296", "26a451d7dddfa1abc28595e8c4e84888", "b2230dc319aa2f483910ad0494bd93ae", "d390b2ff1538ee01abe51b5f8aa47fd5", "ee5d9e30c8fd710229b5e7bcad9bea49", "9eb496c06fadc1c52c1afaca67d4eb20", "a7df3192e490db7dc9b341541940c8ae", "3f4472228e18b2c3ebc2c40a8cfa58a6", "ff0a760218e45f92e3df0481d45ed6fc", "b1bb5bd18467e9a8004878ecf8991285", "e55e6fec51baa038243727b2f9f13716", "cd5a1543a83ef4ef5fe9aee31169897d", "11b4b1789c8a018402117893ffe8704c", "e846c9bba201095aad00f66984938e63", "d4222164ced631e497ba4c79b339376c", "7b76ecbc496d7ef567e5451f960d0f57", "7c14897f62c64f4e2e516ce0b11ba232", "6fa21641ada1c57e16d7a352a850763c", "f92a0fe46151657803ac8fbd7eaaf4f9", "0fd1c09ca234c77d606d31d75f200b8f", "ae48699bb068e1df6e817e3c241e818c", "cfd0462dc6f09ee7aac65b304fd2ea0e", "7d672dc1748866f2cee2272e6a2173ec", "773c044cec4c2e18730c740bf7b9c057", "4837583a7a4ceb607611eb4d92fb359e", "6efdfddff5920f4b846fd3b8ff4bcce9", "8d670857f5faee232ecae1b4d52b6009", "fe989d70079bdbf8bf15f0f632da983f", "6bc8646dd1158768cf8de10b7f0383e3", "e1d03fbba00f3565017c6d66112a162c", "c8fb54cef61119d544dcdb81f9bb623e", "a32ee28fc12017d6e89b8be39c762706", "1d771b0f196333fe8c6fb8ba3871e7bb", "b60a7cf7c844db94ff915bb7bf7c01da", "e2e2facba108472d07375c28018d95f3", "09e05aca7cc5880d6234c1a1ede68e5e", "20799eb08c22ec6a6323d5a1fbbd6672", "18278248af340dd4de692e53033af59e", "8c3eb0869a5a9cc7c6c25a7279871c2d", "fc512d93b37e3b575792ad6191ab2899", "f488916d0fd4a18395688eefe1373ee9", "c36e563592d152c916dd537cc4601bb8", "cb9ecdada2fecb81bb09abf86be63251", "0802fd9d6f49deb846fc68fa5b4334ec", "3a99b70264f0fa9630cba122fa357715", "387fb5446cfdde442b6ea2fbde849058", "9deb5c90711d74fb9b9749d528cecb6b", "86c91f07088a3d818cc486b1b74d98a9", "7cc9f404a3d227a9f9caa5d1f1519e2b", "2a67105d0efb96c95a36384de3027db9", "cb621e7f7b2aaf23c3d00e118f75485e", "f4ce9eca6b677024501af8b28158f75c", "5b17dc663b9db1714e1969fe656c89b6", "6d05c3e28fecd626b33581100d762969", "e664663478597ece6e170c2713c0eb2a", "e270c300fc0be2fe4b9897226bcfd66a", "555ade606a292ddea2deac99de99c405", "1b6354bf2b58f13dbf3e864d8d0341b6", "0147d0c2edf4379cf3b2aeafd6a8e8eb", "031f000771949093e95fd7fc1a713864", "760e531a0ef4ac1b84266520b06dd0ed", "59167f11b20d76dee5d95bc87c622de4", "50e845ce10b81010c9c156da5c65a999", "e7f32184cf87dbeb58edf270bdb7eff0", "b247eed927808bed6bc10f7e08eeb97c", "f1ab40357283700398a39396f456b0ff", "a4d3c046a463da30f918e308197b2080", "44641b97a6fc01eade6e49f8c7dc9eef", "2b27f7cb5c06df6a5d022658f602484c", "6716b29658842faf9c3a271336bd2242", "8008d10332edba97d6ba6a9cba007810", "87ee590e16f572bd475d90fa73426cc7", "87faa1ef752f491a6ab7751543cd7ba0", "e330bcd7fc2f7992c7e91f36d0252e6a", "2b74ea75ae0971f7d2b2cf9b3e883b2c", "f9372ecbd57d37eed183c9fe267734f6", "13636109d7cbb0607bf2528cab420561", "6da0b15f6244dda40e1db48b6760bfc3", "3faeea6fca6d5fd7133c8019dab3c659", "ea7b2bd439d98b0f4917da16ad427c6b", "f58a533ad363b70e4c3c12c8bbd4ca05", "6d1b011450c484e847464fa491bbf65a", "f53a255fc0902c66a972e9d41692905c", "d2f8309cc1bf875d53a5963dbeef5aa8", "84c77a3b4ad854b3b0399c3c54d58cc6", "f7977100857408a1099d721521f9e38c", "0bc1312f32880ca921876a66877e3ed3", "c625a746fcf68d5088a01793b1764e61", "55f84687c80bca82081f33282da4af0e", "2a8f0f9efbc23e2d087ebdaf72207303", "75c9783a6087463feafbf286461d1bcd", "b00ebd5dcfc129a3045fed69e13256ff", "3a7e4ef5bc43f45df8239a12b7cde150", "98e7cc4f28208efc42da2c121fc5e12d", "98d41ff93ccbb09c6fc2b6fa41e63681", "7045ad0b8de1ecff1658b63ab16c44d2", "fe878f98d80dbf1d689545fee16fb239", "3e5628afd83878093ad17babdf43bc7b", "252f880618d2fa78cfdf6f353dd3cbba", "22eb8db591448cf53f25b735cb13d7de", "9582bb874589cee6410b915659817579", "fb3da678bb24d114197f5c9b3956abe3", "82a725582d1b5e2229ea165c4d2a0a33", "e70b4c87a9c49ffbf1393cd513946b83", "91a7f255b0958a6e325e6cb9de2dbc4f", "6c153ad9460c49534a201523946db7d1", "bb5fd912f827e224e8fa429f8b92908c", "715048ba8b862fba231b84874300541f", "c7dc11268929037c2828ca57f342f7de", "b1fd824d83560048d749317734f99a47", "56248687c34175a54c07adaf62cd9951", "92001e4400135444031ae2f7cacb1c73", "3a239f05fce9acbe2983c723c42c0047", "749cc65784d1ffb5784aff3f2b060077", "aaf15ab33d35eb3be20bd4ae2a30ee6c", "d6828b8a6c1a84ca83eac48e88f94dd7", "eba5f6f57923a7d8c4d31cdcb899ebf4", "f2f54348e2b894e06dcf1ed063f726bd", "039ceddc6c9e52539e841c7d832bea1f", "b43a54e57fe48b2b21246e98c4138d6c", "d3e605f69121c87edfaaba58f36d1963", "a7d749cf1730918829f9a501fc051ed1", "4f2a350da2fd7c8e3bd95019dc74c308", "e262b035bc9c75b18e7d351e5406a9e6", "811360778e5c7218e1b6cbc2b272ffa3", "2e131e21be41b8afe7590d639eacb032", "28d96195df4e9f13d4828d37efa560d0", "2197c84a977d74db9040811b0f7c66b8", "dc49eef602e4e75cfd2c1644a4113cd2", "c3b42b11ada21d1df15257363c8729d6", "fead731914e63c2684f554c359a9e69c", "242ebc132b173d1efaa4b589c2488653", "e9e196fedf16441246b71ff52cc89ae4", "c3af83626bd88b88353e0ea8ef4eaebb", "3854491d00cd2b29ef5eb0aea316bc8f", "abce0e94c890609a6c1d59473b9f74e3", "9623894e7c107a53fe48299951db5e93", "47e4b04a58c05479cd8ba22bf09495df", "decf11abe9eea47903e8f03cc60aa8e7", "d30e6866430f6b5396a158beeaa98bd0", "580ff775d570e0af31d5790976d93b62", "93cee1adf53fc9f0f7ca27e8bccd47da", "de4ab6d7ed1fc15d518cb972d35d3fe8", "917e83b96e8b3467c749b703a2a54dac", "dac09042a49b86322102e8995ffa5448", "6384b657618e6a2b1ebd587179b04220", "e6e85d14ae92073bf127b001e2b149fc", "6246b53a2be4fb00e0d6e4881d2e28f3", "4d04f67d0fdc4b57b335f7aa8dfc176f", "3954ba8553eca604d07fcc094a62f439", "130da9c93262607fb169f6dcf5843436"], "id_to_hash": {"000": "9deb5c90711d74fb9b9749d528cecb6b", "001": "40ed71c0a344839367ffddc61d277a4a", "002": "6d1b011450c484e847464fa491bbf65a", "003": "fe878f98d80dbf1d689545fee16fb239", "004": "fb9b91e540d93b6b2d2bf138e1d99e30", "005": "0bc1312f32880ca921876a66877e3ed3", "006": "e664663478597ece6e170c2713c0eb2a", "007": "f935909891e9df8f5c6d5d6eb1847929", "008": "26a451d7dddfa1abc28595e8c4e84888", "009": "6956535727e4d6cd4d5fb8fd9ee3bc23", "010": "b00ebd5dcfc129a3045fed69e13256ff", "011": "b247eed927808bed6bc10f7e08eeb97c", "012": "d30e6866430f6b5396a158beeaa98bd0", "013": "a4d3c046a463da30f918e308197b2080", "014": "c3af83626bd88b88353e0ea8ef4eaebb", "015": "2b27f7cb5c06df6a5d022658f602484c", "016": "b93b8e46fe56346ca613354a30b2a0f3", "017": "2a8f0f9efbc23e2d087ebdaf72207303", "018": "252f880618d2fa78cfdf6f353dd3cbba", "019": "ae86fcb44a462abe39a4284cc576df7d", "020": "e270c300fc0be2fe4b9897226bcfd66a", "021": "6fa21641ada1c57e16d7a352a850763c", "022": "7dd7af5c78f673a3d0e59314f11db5b6", "023": "6384b657618e6a2b1ebd587179b04220", "024": "84c77a3b4ad854b3b0399c3c54d58cc6", "025": "d2f8309cc1bf875d53a5963dbeef5aa8", "026": "4837583a7a4ceb607611eb4d92fb359e", "027": "86c91f07088a3d818cc486b1b74d98a9", "028": "4d04f67d0fdc4b57b335f7aa8dfc176f", "029": "2e131e21be41b8afe7590d639eacb032", "030": "09e05aca7cc5880d6234c1a1ede68e5e", "031": "039ceddc6c9e52539e841c7d832bea1f", "032": "b2230dc319aa2f483910ad0494bd93ae", "033": "fead731914e63c2684f554c359a9e69c", "034": "493ce4cebc7ae4d31603b1926a46f18d", "035": "b61b435b07572cd437577369271f3113", "036": "28bf55258a4338e0c4e24286e432162f", "037": "555ade606a292ddea2deac99de99c405", "038": "f1ab40357283700398a39396f456b0ff", "039": "b9628d8665064b807eb2ccfe774c8808", "040": "3a119050249b0cb2761edf60d08bb8ed", "041": "0308d02fc1dabf340e74cdcb4b216f9f", "042": "6c153ad9460c49534a201523946db7d1", "043": "6b13932ee7ea8f8a68cfd00e010beac8", "044": "f6cb30c38a97d5b084128bad7b1839e0", "045": "59167f11b20d76dee5d95bc87c622de4", "046": "cfd0462dc6f09ee7aac65b304fd2ea0e", "047": "2b18f8178919d2ed2513efad489c46f4", "048": "6efdfddff5920f4b846fd3b8ff4bcce9", "049": "3a99b70264f0fa9630cba122fa357715", "050": "760e531a0ef4ac1b84266520b06dd0ed", "051": "978e70615695cba74f6e77aff7bc5107", "052": "d3e605f69121c87edfaaba58f36d1963", "053": "130da9c93262607fb169f6dcf5843436", "054": "2e944273885bd9265d94b2a7e9b4d4eb", "055": "e7f32184cf87dbeb58edf270bdb7eff0", "056": "50e845ce10b81010c9c156da5c65a999", "057": "a32ee28fc12017d6e89b8be39c762706", "058": "bbe22e00ea6e37e7aa61f607a9bd45d9", "059": "de4ab6d7ed1fc15d518cb972d35d3fe8", "060": "e55e6fec51baa038243727b2f9f13716", "061": "b43a54e57fe48b2b21246e98c4138d6c", "062": "8c3eb0869a5a9cc7c6c25a7279871c2d", "063": "75c9783a6087463feafbf286461d1bcd", "064": "3954ba8553eca604d07fcc094a62f439", "065": "ddce2097be3eebc6c4a64deac3a8e5ba", "066": "4704e8b36fc8dcae70e49b9818ab4215", "067": "87ee590e16f572bd475d90fa73426cc7", "068": "6bc8646dd1158768cf8de10b7f0383e3", "069": "20799eb08c22ec6a6323d5a1fbbd6672", "070": "bb5fd912f827e224e8fa429f8b92908c", "071": "9eb496c06fadc1c52c1afaca67d4eb20", "072": "7d672dc1748866f2cee2272e6a2173ec", "073": "13636109d7cbb0607bf2528cab420561", "074": "7045ad0b8de1ecff1658b63ab16c44d2", "075": "82a725582d1b5e2229ea165c4d2a0a33", "076": "c3b42b11ada21d1df15257363c8729d6", "077": "0147d0c2edf4379cf3b2aeafd6a8e8eb", "078": "f2592e7f3e0eb2991c18012268e5b3b9", "079": "c36e563592d152c916dd537cc4601bb8", "080": "a7df3192e490db7dc9b341541940c8ae", "081": "6da0b15f6244dda40e1db48b6760bfc3", "082": "1b54b2ede16e50fcd7d4747027dc2072", "083": "2197c84a977d74db9040811b0f7c66b8", "084": "2a67105d0efb96c95a36384de3027db9", "085": "1b6354bf2b58f13dbf3e864d8d0341b6", "086": "3faeea6fca6d5fd7133c8019dab3c659", "087": "98d41ff93ccbb09c6fc2b6fa41e63681", "088": "3e5628afd83878093ad17babdf43bc7b", "089": "28d96195df4e9f13d4828d37efa560d0", "090": "02f980092269d49c8a5c169f66e2a3f5", "091": "dac09042a49b86322102e8995ffa5448", "092": "9623894e7c107a53fe48299951db5e93", "093": "cd5a1543a83ef4ef5fe9aee31169897d", "094": "644f62971fc31354275f81d7254bfe57", "095": "55f84687c80bca82081f33282da4af0e", "096": "0fd1c09ca234c77d606d31d75f200b8f", "097": "91a7f255b0958a6e325e6cb9de2dbc4f", "098": "06045fccc6384f5f13f7b7d275992c54", "099": "b19e601ae8d231a6ed244d1dc4713eff", "100": "a7d749cf1730918829f9a501fc051ed1", "101": "cb621e7f7b2aaf23c3d00e118f75485e", "102": "fe989d70079bdbf8bf15f0f632da983f", "103": "4f2a350da2fd7c8e3bd95019dc74c308", "104": "3f4472228e18b2c3ebc2c40a8cfa58a6", "105": "2b74ea75ae0971f7d2b2cf9b3e883b2c", "106": "3854491d00cd2b29ef5eb0aea316bc8f", "107": "87faa1ef752f491a6ab7751543cd7ba0", "108": "f58a533ad363b70e4c3c12c8bbd4ca05", "109": "53965d1a71cafa0a66c91486fd89daf9", "110": "d390b2ff1538ee01abe51b5f8aa47fd5", "111": "031f000771949093e95fd7fc1a713864", "112": "3a239f05fce9acbe2983c723c42c0047", "113": "242ebc132b173d1efaa4b589c2488653", "114": "22eb8db591448cf53f25b735cb13d7de", "115": "4979638815b14ec2ae67d5aa8ddfbe24", "116": "f53a255fc0902c66a972e9d41692905c", "117": "4d41175d626ac093f9dd53e857f89714", "118": "f92a0fe46151657803ac8fbd7eaaf4f9", "119": "eb410acb3dfa34b6b906f80aeb50ec33", "120": "d4222164ced631e497ba4c79b339376c", "121": "cb9ecdada2fecb81bb09abf86be63251", "122": "f4ce9eca6b677024501af8b28158f75c", "123": "5b9ae7c1cb17d4dc5e5db93da254b099", "124": "c8fb54cef61119d544dcdb81f9bb623e", "125": "917e83b96e8b3467c749b703a2a54dac", "126": "5014d28977f52eded1898f008862e578", "127": "dc49eef602e4e75cfd2c1644a4113cd2", "128": "47e4b04a58c05479cd8ba22bf09495df", "129": "4ab5fc26ca1d6be4efb463516811122e", "130": "3d46e261b3358965c36da7f8e5dfbbd4", "131": "773c044cec4c2e18730c740bf7b9c057", "132": "e6b2bf50f832321d1a7ee989d257b42f", "133": "8d670857f5faee232ecae1b4d52b6009", "134": "3d53be6da553f3ff10862297b6e918e6", "135": "f9372ecbd57d37eed183c9fe267734f6", "136": "c625a746fcf68d5088a01793b1764e61", "137": "41776741a182f625a2df8842a2ee59e7", "138": "0802fd9d6f49deb846fc68fa5b4334ec", "139": "ee309d77abd0848eef989782b9b545a5", "140": "56248687c34175a54c07adaf62cd9951", "141": "387fb5446cfdde442b6ea2fbde849058", "142": "decf11abe9eea47903e8f03cc60aa8e7", "143": "9582bb874589cee6410b915659817579", "144": "e1d03fbba00f3565017c6d66112a162c", "145": "fb3da678bb24d114197f5c9b3956abe3", "146": "d8ba8477cff1af51891c3d1586e40296", "147": "7cc9f404a3d227a9f9caa5d1f1519e2b", "148": "c7dc11268929037c2828ca57f342f7de", "149": "11b4b1789c8a018402117893ffe8704c", "150": "aaf15ab33d35eb3be20bd4ae2a30ee6c", "151": "6b21dcf618e4cdfaf7f10319abb3f709", "152": "44641b97a6fc01eade6e49f8c7dc9eef", "153": "ae48699bb068e1df6e817e3c241e818c", "154": "5b17dc663b9db1714e1969fe656c89b6", "155": "3a7e4ef5bc43f45df8239a12b7cde150", "156": "ea7b2bd439d98b0f4917da16ad427c6b", "157": "b1bb5bd18467e9a8004878ecf8991285", "158": "8008d10332edba97d6ba6a9cba007810", "159": "f488916d0fd4a18395688eefe1373ee9", "160": "98e7cc4f28208efc42da2c121fc5e12d", "161": "18278248af340dd4de692e53033af59e", "162": "1d771b0f196333fe8c6fb8ba3871e7bb", "163": "6716b29658842faf9c3a271336bd2242", "164": "e262b035bc9c75b18e7d351e5406a9e6", "165": "f2f54348e2b894e06dcf1ed063f726bd", "166": "e846c9bba201095aad00f66984938e63", "167": "715048ba8b862fba231b84874300541f", "168": "e6e85d14ae92073bf127b001e2b149fc", "169": "749cc65784d1ffb5784aff3f2b060077", "170": "c07089798ca0bae26808eb35eaaf82de", "171": "92001e4400135444031ae2f7cacb1c73", "172": "93cee1adf53fc9f0f7ca27e8bccd47da", "173": "6246b53a2be4fb00e0d6e4881d2e28f3", "174": "d43e1d4b8cb42f7b7b2106eabf58157c", "175": "580ff775d570e0af31d5790976d93b62", "176": "f7977100857408a1099d721521f9e38c", "177": "8beb19396b632eae86f8e0aa051516c2", "178": "abce0e94c890609a6c1d59473b9f74e3", "179": "e9e196fedf16441246b71ff52cc89ae4", "180": "6d05c3e28fecd626b33581100d762969", "181": "e330bcd7fc2f7992c7e91f36d0252e6a", "182": "d6828b8a6c1a84ca83eac48e88f94dd7", "183": "b60a7cf7c844db94ff915bb7bf7c01da", "184": "ff0a760218e45f92e3df0481d45ed6fc", "185": "9ce49cda8497f2d37d7e7ec1c08f17aa", "186": "1209f43304bbf42b0b116b7f6571a5e9", "187": "e2e2facba108472d07375c28018d95f3", "188": "e7e209e9a2b65a1e5c6222d1f2b833a7", "189": "b1fd824d83560048d749317734f99a47", "190": "7c14897f62c64f4e2e516ce0b11ba232", "191": "e70b4c87a9c49ffbf1393cd513946b83", "192": "eba5f6f57923a7d8c4d31cdcb899ebf4", "193": "ee5d9e30c8fd710229b5e7bcad9bea49", "194": "fc512d93b37e3b575792ad6191ab2899", "195": "811360778e5c7218e1b6cbc2b272ffa3", "196": "1e2c8c15591647bc5e85289f7e337c7d", "197": "4c458dffba36748af2acdcd89f701c92", "198": "f943b653ba7dd1a79c3427b1ee5bcb95", "199": "7b76ecbc496d7ef567e5451f960d0f57"}, "display": {"search_start": "2024-05-27T20:14:21.719422", "trial_start": {"000": "2024-05-27T20:14:21.719422", "001": "2024-05-27T20:14:53.343849", "002": "2024-05-27T20:15:14.560307", "003": "2024-05-27T20:15:35.848165", "004": "2024-05-27T20:15:56.803697", "005": "2024-05-27T20:16:15.947053", "006": "2024-05-27T20:16:34.919445", "007": "2024-05-27T20:16:59.326767", "008": "2024-05-27T20:17:20.880348", "009": "2024-05-27T20:17:45.404932", "010": "2024-05-27T20:18:12.740624", "011": "2024-05-27T20:18:31.348233", "012": "2024-05-27T20:18:53.773761", "013": "2024-05-27T20:19:17.206556", "014": "2024-05-27T20:19:35.231764", "015": "2024-05-27T20:19:56.980074", "016": "2024-05-27T20:20:16.429639", "017": "2024-05-27T20:20:41.883023", "018": "2024-05-27T20:21:01.975404", "019": "2024-05-27T20:21:27.697904", "020": "2024-05-27T20:21:49.093685", "021": "2024-05-27T20:22:10.105442", "022": "2024-05-27T20:22:29.014798", "023": "2024-05-27T20:22:48.487591", "024": "2024-05-27T20:23:11.943801", "025": "2024-05-27T20:23:34.075707", "026": "2024-05-27T20:24:03.824731", "027": "2024-05-27T20:24:29.008562", "028": "2024-05-27T20:25:00.963924", "029": "2024-05-27T20:25:27.655446", "030": "2024-05-27T20:25:53.580605", "031": "2024-05-27T20:26:16.770575", "032": "2024-05-27T20:26:42.030632", "033": "2024-05-27T20:27:04.654195", "034": "2024-05-27T20:27:27.150764", "035": "2024-05-27T20:27:48.952005", "036": "2024-05-27T20:28:19.998853", "037": "2024-05-27T20:28:42.512534", "038": "2024-05-27T20:29:03.688676", "039": "2024-05-27T20:29:26.964661", "040": "2024-05-27T20:29:50.851368", "041": "2024-05-27T20:30:18.562021", "042": "2024-05-27T20:30:47.715102", "043": "2024-05-27T20:31:10.082859", "044": "2024-05-27T20:31:35.681413", "045": "2024-05-27T20:32:09.979332", "046": "2024-05-27T20:32:33.952957", "047": "2024-05-27T20:32:58.357212", "048": "2024-05-27T20:33:36.821773", "049": "2024-05-27T20:33:58.737558", "050": "2024-05-27T20:34:24.358456", "051": "2024-05-27T20:34:48.873188", "052": "2024-05-27T20:35:17.811890", "053": "2024-05-27T20:35:40.678353", "054": "2024-05-27T20:36:05.496156", "055": "2024-05-27T20:36:28.501763", "056": "2024-05-27T20:36:54.327408", "057": "2024-05-27T20:37:18.593727", "058": "2024-05-27T20:37:46.649495", "059": "2024-05-27T20:38:11.422172", "060": "2024-05-27T20:39:17.558687", "061": "2024-05-27T20:39:47.272939", "062": "2024-05-27T20:40:10.563367", "063": "2024-05-27T21:00:13.520848", "064": "2024-05-27T21:00:19.345972", "065": "2024-05-27T21:00:27.652527", "066": "2024-05-27T21:00:32.608221", "067": "2024-05-27T21:00:46.269868", "068": "2024-05-27T21:00:54.450175", "069": "2024-05-27T21:01:02.488424", "070": "2024-05-27T21:01:18.370940", "071": "2024-05-27T21:01:21.908923", "072": "2024-05-27T21:01:26.446404", "073": "2024-05-27T21:01:31.319473", "074": "2024-05-27T21:01:37.361469", "075": "2024-05-27T21:01:42.593978", "076": "2024-05-27T21:01:45.970570", "077": "2024-05-27T21:01:52.318085", "078": "2024-05-27T21:01:56.312416", "079": "2024-05-27T21:02:06.168041", "080": "2024-05-27T21:02:09.342757", "081": "2024-05-27T21:02:15.213007", "082": "2024-05-27T21:02:20.807435", "083": "2024-05-27T21:02:25.953395", "084": "2024-05-27T21:02:31.740601", "085": "2024-05-27T21:02:37.897770", "086": "2024-05-27T21:02:45.431810", "087": "2024-05-27T21:02:52.715153", "088": "2024-05-27T21:02:59.128551", "089": "2024-05-27T21:03:11.426491", "090": "2024-05-27T21:03:17.519123", "091": "2024-05-27T21:03:26.881877", "092": "2024-05-27T21:03:30.874867", "093": "2024-05-27T21:03:35.263452", "094": "2024-05-27T21:03:39.031220", "095": "2024-05-27T21:03:47.641204", "096": "2024-05-27T21:03:53.478944", "097": "2024-05-27T21:04:10.498553", "098": "2024-05-27T21:04:16.915234", "099": "2024-05-27T21:04:24.016912", "100": "2024-05-27T21:04:29.942430", "101": "2024-05-27T21:04:37.061705", "102": "2024-05-27T21:04:43.937335", "103": "2024-05-27T21:04:52.319905", "104": "2024-05-27T21:05:01.728350", "105": "2024-05-27T21:05:10.098057", "106": "2024-05-27T21:05:17.260265", "107": "2024-05-27T21:05:24.069307", "108": "2024-05-27T21:05:29.274033", "109": "2024-05-27T21:05:35.893081", "110": "2024-05-27T21:05:44.912741", "111": "2024-05-27T21:05:53.254487", "112": "2024-05-27T21:06:03.265696", "113": "2024-05-27T21:06:10.182776", "114": "2024-05-27T21:06:15.600451", "115": "2024-05-27T21:06:22.293192", "116": "2024-05-27T21:06:42.617430", "117": "2024-05-27T21:06:52.718595", "118": "2024-05-27T21:07:00.111307", "119": "2024-05-27T21:07:08.025979", "120": "2024-05-27T21:07:26.166427", "121": "2024-05-27T21:07:38.986622", "122": "2024-05-27T21:07:43.972026", "123": "2024-05-27T21:07:56.215642", "124": "2024-05-27T21:08:10.963296", "125": "2024-05-27T21:08:19.219156", "126": "2024-05-27T21:08:29.236157", "127": "2024-05-27T21:08:36.621125", "128": "2024-05-27T21:08:53.094735", "129": "2024-05-27T21:09:03.390387", "130": "2024-05-27T21:09:09.010511", "131": "2024-05-27T21:09:17.271552", "132": "2024-05-27T21:09:33.743104", "133": "2024-05-27T21:09:44.905049", "134": "2024-05-27T21:09:50.714371", "135": "2024-05-27T21:09:57.891175", "136": "2024-05-27T21:10:02.281973", "137": "2024-05-27T21:10:10.396794", "138": "2024-05-27T21:10:29.344774", "139": "2024-05-27T21:10:55.557922", "140": "2024-05-27T21:11:06.923112", "141": "2024-05-27T21:11:16.846551", "142": "2024-05-27T21:11:22.045903", "143": "2024-05-27T21:11:27.160988", "144": "2024-05-27T21:11:35.402915", "145": "2024-05-27T21:11:42.300467", "146": "2024-05-27T21:11:47.974821", "147": "2024-05-27T21:11:55.135847", "148": "2024-05-27T21:12:12.356424", "149": "2024-05-27T21:12:24.342315", "150": "2024-05-27T21:12:37.509905", "151": "2024-05-27T21:12:48.422090", "152": "2024-05-27T21:12:55.517170", "153": "2024-05-27T21:13:06.245931", "154": "2024-05-27T21:13:24.848210", "155": "2024-05-27T21:13:32.335639", "156": "2024-05-27T21:13:49.741559", "157": "2024-05-27T21:14:07.181022", "158": "2024-05-27T21:14:16.541557", "159": "2024-05-27T21:14:22.571585", "160": "2024-05-27T21:14:31.087812", "161": "2024-05-27T21:14:47.700587", "162": "2024-05-27T21:15:03.228179", "163": "2024-05-27T21:15:10.409034", "164": "2024-05-27T21:15:18.374067", "165": "2024-05-27T21:15:26.070890", "166": "2024-05-27T21:15:39.965359", "167": "2024-05-27T21:15:50.748067", "168": "2024-05-27T21:15:58.137118", "169": "2024-05-27T21:16:06.296890", "170": "2024-05-27T21:16:12.684205", "171": "2024-05-27T21:16:22.445866", "172": "2024-05-27T21:16:32.539869", "173": "2024-05-27T21:16:40.336171", "174": "2024-05-27T21:16:55.230182", "175": "2024-05-27T21:17:06.610148", "176": "2024-05-27T21:17:21.572176", "177": "2024-05-27T21:17:27.523894", "178": "2024-05-27T21:17:36.844136", "179": "2024-05-27T21:17:57.400154", "180": "2024-05-27T21:18:05.920893", "181": "2024-05-27T21:18:18.327340", "182": "2024-05-27T21:18:30.306548", "183": "2024-05-27T21:18:38.303560", "184": "2024-05-27T21:18:45.978217", "185": "2024-05-27T21:18:55.365971", "186": "2024-05-27T21:19:04.026419", "187": "2024-05-27T21:19:21.275059", "188": "2024-05-27T21:19:28.885305", "189": "2024-05-27T21:19:43.128269", "190": "2024-05-27T21:19:51.509389", "191": "2024-05-27T21:20:25.730413", "192": "2024-05-27T21:20:31.584103", "193": "2024-05-27T21:20:40.006203", "194": "2024-05-27T21:20:46.583230", "195": "2024-05-27T21:20:54.779046", "196": "2024-05-27T21:21:04.585190", "197": "2024-05-27T21:21:14.103605", "198": "2024-05-27T21:21:22.030856", "199": "2024-05-27T21:21:29.345721"}, "trial_number": {"000": 1, "001": 2, "002": 3, "003": 4, "004": 5, "005": 6, "006": 7, "007": 8, "008": 9, "009": 10, "010": 11, "011": 12, "012": 13, "013": 14, "014": 15, "015": 16, "016": 17, "017": 18, "018": 19, "019": 20, "020": 21, "021": 22, "022": 23, "023": 24, "024": 25, "025": 26, "026": 27, "027": 28, "028": 29, "029": 30, "030": 31, "031": 32, "032": 33, "033": 34, "034": 35, "035": 36, "036": 37, "037": 38, "038": 39, "039": 40, "040": 41, "041": 42, "042": 43, "043": 44, "044": 45, "045": 46, "046": 47, "047": 48, "048": 49, "049": 50, "050": 51, "051": 52, "052": 53, "053": 54, "054": 55, "055": 56, "056": 57, "057": 58, "058": 59, "059": 60, "060": 61, "061": 62, "062": 63, "063": 64, "064": 65, "065": 66, "066": 67, "067": 68, "068": 69, "069": 70, "070": 71, "071": 72, "072": 73, "073": 74, "074": 75, "075": 76, "076": 77, "077": 78, "078": 79, "079": 80, "080": 81, "081": 82, "082": 83, "083": 84, "084": 85, "085": 86, "086": 87, "087": 88, "088": 89, "089": 90, "090": 91, "091": 92, "092": 93, "093": 94, "094": 95, "095": 96, "096": 97, "097": 98, "098": 99, "099": 100, "100": 101, "101": 102, "102": 103, "103": 104, "104": 105, "105": 106, "106": 107, "107": 108, "108": 109, "109": 110, "110": 111, "111": 112, "112": 113, "113": 114, "114": 115, "115": 116, "116": 117, "117": 118, "118": 119, "119": 120, "120": 121, "121": 122, "122": 123, "123": 124, "124": 125, "125": 126, "126": 127, "127": 128, "128": 129, "129": 130, "130": 131, "131": 132, "132": 133, "133": 134, "134": 135, "135": 136, "136": 137, "137": 138, "138": 139, "139": 140, "140": 141, "141": 142, "142": 143, "143": 144, "144": 145, "145": 146, "146": 147, "147": 148, "148": 149, "149": 150, "150": 151, "151": 152, "152": 153, "153": 154, "154": 155, "155": 156, "156": 157, "157": 158, "158": 159, "159": 160, "160": 161, "161": 162, "162": 163, "163": 164, "164": 165, "165": 166, "166": 167, "167": 168, "168": 169, "169": 170, "170": 171, "171": 172, "172": 173, "173": 174, "174": 175, "175": 176, "176": 177, "177": 178, "178": 179, "179": 180, "180": 181, "181": 182, "182": 183, "183": 184, "184": 185, "185": 186, "186": 187, "187": 188, "188": 189, "189": 190, "190": 191, "191": 192, "192": 193, "193": 194, "194": 195, "195": 196, "196": 197, "197": 198, "198": 199, "199": 200}}}