{"trial_id": "063", "hyperparameters": {"space": [{"class_name": "Int", "config": {"name": "filters", "default": null, "conditions": [], "min_value": 10, "max_value": 150, "step": 5, "sampling": "linear"}}, {"class_name": "Choice", "config": {"name": "pool_size", "default": 2, "conditions": [], "values": [2, 3], "ordered": true}}, {"class_name": "Choice", "config": {"name": "learning_rate", "default": 0.01, "conditions": [], "values": [0.01, 0.001, 0.0001], "ordered": true}}], "values": {"filters": 50, "pool_size": 2, "learning_rate": 0.01}}, "metrics": {"metrics": {"accuracy": {"direction": "max", "observations": [{"value": [0.7551020383834839], "step": 22}]}, "loss": {"direction": "min", "observations": [{"value": [0.5165191888809204], "step": 22}]}, "val_accuracy": {"direction": "max", "observations": [{"value": [0.6129032373428345], "step": 22}]}, "val_loss": {"direction": "min", "observations": [{"value": [0.8168059587478638], "step": 22}]}}}, "score": 0.6129032373428345, "best_step": 22, "status": "COMPLETED", "message": null}