{"trial_id": "123", "hyperparameters": {"space": [{"class_name": "Int", "config": {"name": "filters", "default": null, "conditions": [], "min_value": 10, "max_value": 150, "step": 5, "sampling": "linear"}}, {"class_name": "Choice", "config": {"name": "pool_size", "default": 2, "conditions": [], "values": [2, 3], "ordered": true}}, {"class_name": "Choice", "config": {"name": "learning_rate", "default": 0.01, "conditions": [], "values": [0.01, 0.001, 0.0001], "ordered": true}}], "values": {"filters": 35, "pool_size": 2, "learning_rate": 0.01}}, "metrics": {"metrics": {"accuracy": {"direction": "max", "observations": [{"value": [0.5373134613037109], "step": 12}]}, "loss": {"direction": "min", "observations": [{"value": [0.6875705122947693], "step": 12}]}, "val_accuracy": {"direction": "max", "observations": [{"value": [0.520900309085846], "step": 12}]}, "val_loss": {"direction": "min", "observations": [{"value": [0.6947863101959229], "step": 12}]}}}, "score": 0.520900309085846, "best_step": 12, "status": "COMPLETED", "message": null}