{"trial_id": "088", "hyperparameters": {"space": [{"class_name": "Int", "config": {"name": "filters", "default": null, "conditions": [], "min_value": 10, "max_value": 150, "step": 5, "sampling": "linear"}}, {"class_name": "Choice", "config": {"name": "pool_size", "default": 2, "conditions": [], "values": [2, 3], "ordered": true}}, {"class_name": "Choice", "config": {"name": "learning_rate", "default": 0.01, "conditions": [], "values": [0.01, 0.001, 0.0001], "ordered": true}}], "values": {"filters": 145, "pool_size": 2, "learning_rate": 0.01}}, "metrics": {"metrics": {"loss": {"direction": "min", "observations": [{"value": [645476.125], "step": 3}]}, "mae": {"direction": "min", "observations": [{"value": [600.6190185546875], "step": 3}]}, "mean_absolute_percentage_error": {"direction": "min", "observations": [{"value": [6.810590744018555], "step": 3}]}, "val_loss": {"direction": "min", "observations": [{"value": [13437.6884765625], "step": 3}]}, "val_mae": {"direction": "min", "observations": [{"value": [72.9793472290039], "step": 3}]}, "val_mean_absolute_percentage_error": {"direction": "min", "observations": [{"value": [1.1356782913208008], "step": 3}]}}}, "score": 1.1356782913208008, "best_step": 3, "status": "COMPLETED", "message": null}