{"trial_id": "093", "hyperparameters": {"space": [{"class_name": "Int", "config": {"name": "conv_1_filter", "default": null, "conditions": [], "min_value": 10, "max_value": 150, "step": 10, "sampling": "linear"}}, {"class_name": "Choice", "config": {"name": "pool_1_size", "default": 2, "conditions": [], "values": [2, 3], "ordered": true}}, {"class_name": "Int", "config": {"name": "conv_2_filter", "default": null, "conditions": [], "min_value": 10, "max_value": 150, "step": 10, "sampling": "linear"}}, {"class_name": "Choice", "config": {"name": "pool_2_size", "default": 2, "conditions": [], "values": [2, 3], "ordered": true}}, {"class_name": "Int", "config": {"name": "dense_units", "default": null, "conditions": [], "min_value": 10, "max_value": 200, "step": 10, "sampling": "linear"}}, {"class_name": "Int", "config": {"name": "lstm_units", "default": null, "conditions": [], "min_value": 10, "max_value": 100, "step": 10, "sampling": "linear"}}, {"class_name": "Float", "config": {"name": "dropout_2", "default": 0.1, "conditions": [], "min_value": 0.1, "max_value": 0.5, "step": 0.1, "sampling": "linear"}}, {"class_name": "Choice", "config": {"name": "learning_rate", "default": 0.01, "conditions": [], "values": [0.01, 0.001, 0.0001], "ordered": true}}], "values": {"conv_1_filter": 10, "pool_1_size": 2, "conv_2_filter": 10, "pool_2_size": 2, "dense_units": 70, "lstm_units": 30, "dropout_2": 0.1, "learning_rate": 0.001}}, "metrics": {"metrics": {"loss": {"direction": "min", "observations": [{"value": [5824951.0], "step": 42}]}, "mae": {"direction": "min", "observations": [{"value": [1148.0458984375], "step": 42}]}, "mean_absolute_percentage_error": {"direction": "min", "observations": [{"value": [9.155936241149902], "step": 42}]}, "val_loss": {"direction": "min", "observations": [{"value": [398101.15625], "step": 42}]}, "val_mae": {"direction": "min", "observations": [{"value": [416.24517822265625], "step": 42}]}, "val_mean_absolute_percentage_error": {"direction": "min", "observations": [{"value": [1.941820740699768], "step": 42}]}}}, "score": 1.941820740699768, "best_step": 42, "status": "COMPLETED", "message": null}