{"trial_id": "138", "hyperparameters": {"space": [{"class_name": "Int", "config": {"name": "filters", "default": null, "conditions": [], "min_value": 10, "max_value": 150, "step": 5, "sampling": "linear"}}, {"class_name": "Choice", "config": {"name": "pool_size", "default": 2, "conditions": [], "values": [2, 3], "ordered": true}}, {"class_name": "Choice", "config": {"name": "learning_rate", "default": 0.01, "conditions": [], "values": [0.01, 0.001, 0.0001], "ordered": true}}], "values": {"filters": 125, "pool_size": 3, "learning_rate": 0.0001}}, "metrics": {"metrics": {"loss": {"direction": "min", "observations": [{"value": [420053.0625], "step": 11}]}, "mae": {"direction": "min", "observations": [{"value": [418.1391906738281], "step": 11}]}, "mean_absolute_percentage_error": {"direction": "min", "observations": [{"value": [4.437505722045898], "step": 11}]}, "val_loss": {"direction": "min", "observations": [{"value": [13563.9296875], "step": 11}]}, "val_mae": {"direction": "min", "observations": [{"value": [76.32500457763672], "step": 11}]}, "val_mean_absolute_percentage_error": {"direction": "min", "observations": [{"value": [1.1874462366104126], "step": 11}]}}}, "score": 1.1874462366104126, "best_step": 11, "status": "COMPLETED", "message": null}